pyHelium/__init__.py
pyHelium/api.py
pyHelium/blockchain/__init__.py
pyHelium/blockchain/hotspot.py
PyHelium-0.1.2.2.1.dist-info/LICENSE
PyHelium-0.1.2.2.1.dist-info/METADATA
PyHelium-0.1.2.2.1.dist-info/WHEEL
PyHelium-0.1.2.2.1.dist-info/top_level.txt
PyHelium-0.1.2.2.1.dist-info/RECORD
