Metadata-Version: 2.1
Name: PyHelium
Version: 0.1.2.2.1
Summary: A simple python package to access Helium network's APi
Home-page: http://pypi.python.org/pypi/PyHelium/
Author: Aimé Risson
Author-email: aime.risson.1@gmail.com
License: Mit License
Platform: UNKNOWN
License-File: LICENSE
Requires-Dist: requests
